nirah/__init__.py
nirah-0.0.2.dist-info/LICENSE
nirah-0.0.2.dist-info/METADATA
nirah-0.0.2.dist-info/WHEEL
nirah-0.0.2.dist-info/top_level.txt
nirah-0.0.2.dist-info/RECORD
