Metadata-Version: 2.1
Name: nirah
Version: 0.0.2
Summary: A package for easily sending messages via the CLI or in python.
Home-page: https://github.com/alexanra-vogt/arke
Author: Alexandra Vogt
Author-email: projects@vogt.systems
License: UNKNOWN
Platform: UNKNOWN
Classifier: Programming Language :: Python :: 3
Classifier: License :: OSI Approved :: MIT License
Classifier: Operating System :: OS Independent
Requires-Python: >=3.6
Requires-Dist: twilio
Requires-Dist: discord.py
